grapy/__init__.py
grapy/request.py
grapy/response.py
grapy/sched.py
grapy/utils.py
grapy/core/__init__.py
grapy/core/base_request.py
grapy/core/base_sched.py
grapy/core/base_spider.py
grapy/core/engine.py
grapy/core/exceptions.py
grapy/core/item.py
grapy-0.1.10.dist-info/METADATA
grapy-0.1.10.dist-info/WHEEL
grapy-0.1.10.dist-info/top_level.txt
grapy-0.1.10.dist-info/RECORD
