Metadata-Version: 2.1
Name: grapy
Version: 0.1.10
Summary: Grapy, a fast high-level screen scraping and web crawling framework for Python 3.3 or later base on asyncio.
Home-page: https://github.com/Lupino/grapy
Author: Li Meng Jun
Author-email: lmjubuntu@gmail.com
License: UNKNOWN
Platform: UNKNOWN
Requires-Dist: asyncio
Requires-Dist: aiohttp
Requires-Dist: beautifulsoup4
Requires-Dist: requests
